{
  "print": {
    "print_target": "C:\\colony_system\\data\\target_images\\single_well\\single_well_target_print.png",
    "sheet_mm": 30.0,
    "dpi": 1200,
    "image_px": [
      1417,
      1417
    ],
    "well_diameter_mm": 19.5,
    "clone_diameter_mm": 0.8,
    "clone_offset_from_well_center_mm": [
      0.7,
      0.45
    ],
    "transparent_outside": false
  },
  "camera_sim": {
    "camera_sim": "C:\\colony_system\\data\\target_images\\single_well\\single_well_camera_sim_5120.bmp",
    "image_size": [
      5120,
      5120
    ],
    "fov_mm": [
      3.0,
      3.0
    ],
    "mm_per_pixel": 0.0005859375,
    "image_center_pixel": [
      2559.5,
      2559.5
    ],
    "clone_center_pixel": [
      3754.166666666667,
      3327.5
    ],
    "clone_diameter_mm": 0.8,
    "clone_diameter_px": 1365.3333333333335,
    "clone_offset_from_image_center_mm": [
      0.7,
      0.45
    ],
    "clone_offset_from_image_center_px": [
      1194.6666666666667,
      768.0
    ]
  }
}